_zengl.py
zengl.cpython-314t-x86_64-linux-gnu.so
zengl-stubs/__init__.pyi
zengl-2.7.2.dist-info/METADATA
zengl-2.7.2.dist-info/WHEEL
zengl-2.7.2.dist-info/top_level.txt
zengl-2.7.2.dist-info/RECORD
zengl-2.7.2.dist-info/licenses/LICENSE
