Metadata-Version: 2.4
Name: zengl
Version: 2.7.2
Summary: OpenGL Pipelines for Python
Home-page: https://github.com/szabolcsdombi/zengl/
Author: Szabolcs Dombi
Author-email: szabolcs@szabolcsdombi.com
License: MIT
Project-URL: Documentation, https://zengl.readthedocs.io/
Project-URL: Source, https://github.com/szabolcsdombi/zengl/
Project-URL: Bug Tracker, https://github.com/szabolcsdombi/zengl/issues/
Keywords: OpenGL,rendering,graphics,shader,gpu
Platform: any
License-File: LICENSE
Dynamic: author
Dynamic: author-email
Dynamic: description
Dynamic: description-content-type
Dynamic: home-page
Dynamic: keywords
Dynamic: license
Dynamic: license-file
Dynamic: platform
Dynamic: project-url
Dynamic: summary
